weather_apiiii/__init__.py
weather_apiiii/api_helper.py
weather_apiiii/configuration.py
weather_apiiii/decorators.py
weather_apiiii/weather_apiiii_client.py
weather_apiiii/controllers/__init__.py
weather_apiiii/controllers/base_controller.py
weather_apiiii/controllers/find_weather_controller.py
weather_apiiii/exceptions/__init__.py
weather_apiiii/exceptions/api_exception.py
weather_apiiii/http/__init__.py
weather_apiiii/http/http_call_back.py
weather_apiiii/http/http_client.py
weather_apiiii/http/http_context.py
weather_apiiii/http/http_method_enum.py
weather_apiiii/http/http_request.py
weather_apiiii/http/http_response.py
weather_apiiii/http/requests_client.py
weather_apiiii/http/auth/__init__.py
weather_apiiii/http/auth/custom_query_auth.py
weather_apiiii/models/__init__.py
weather_apiiii/models/city_weather.py
weather_apiiii/models/clouds.py
weather_apiiii/models/coord.py
weather_apiiii/models/list.py
weather_apiiii/models/main.py
weather_apiiii/models/rain.py
weather_apiiii/models/sys.py
weather_apiiii/models/weather.py
weather_apiiii/models/wind.py
weather_apiiii-1.0.dist-info/LICENSE
weather_apiiii-1.0.dist-info/METADATA
weather_apiiii-1.0.dist-info/WHEEL
weather_apiiii-1.0.dist-info/top_level.txt
weather_apiiii-1.0.dist-info/RECORD
